fpsample-0.3.3.dist-info/METADATA
fpsample-0.3.3.dist-info/WHEEL
fpsample-0.3.3.dist-info/licenses/LICENSE
fpsample/wrapper.py
fpsample/__init__.py
fpsample/fpsample.cpython-310-darwin.so
fpsample-0.3.3.dist-info/RECORD
