Metadata-Version: 2.3
Name: fpsample
Version: 0.3.3
Classifier: Programming Language :: Rust
Classifier: Programming Language :: Python :: Implementation :: CPython
Classifier: Programming Language :: Python :: Implementation :: PyPy
Requires-Dist: numpy >=1.16.0
License-File: LICENSE
Summary: An efficient CPU implementation of farthest point sampling (FPS) for point clouds.
Author-email: Leonard Lin <leonard.keilin@gmail.com>
Requires-Python: >=3.7
Project-URL: Repository, https://github.com/leonardodalinky/fpsample
Project-URL: Tracker, https://github.com/leonardodalinky/fpsample/issues
